astrotrails/__init__.py
astrotrails/astrogui.py
astrotrails/command_line.py
astrotrails-2023.10.13.dist-info/LICENSE.txt
astrotrails-2023.10.13.dist-info/METADATA
astrotrails-2023.10.13.dist-info/WHEEL
astrotrails-2023.10.13.dist-info/entry_points.txt
astrotrails-2023.10.13.dist-info/top_level.txt
astrotrails-2023.10.13.dist-info/RECORD
