Metadata-Version: 2.1
Name: astrotrails
Version: 2023.10.13
Summary: Tool to generate startrails images by stacking consecutive images of nightsky in jpeg format. Also, astrotrails can create a timelapse video.
Author-email: Theo Gatsios <theogat@protonmail.com>
License: MIT License
Keywords: astrophotography,startrails,astrotrails
Classifier: Programming Language :: Python :: 3
Requires-Python: >=3.7
License-File: LICENSE.txt
Requires-Dist: numpy
Requires-Dist: Pillow
Requires-Dist: tqdm
Requires-Dist: ffmpeg
Requires-Dist: customtkinter
Requires-Dist: ttkthemes
